ga_api/__init__.py
ga_api/field_tree.py
ga_api/ga_api_client.py
ga_api/ga_api_client_0.1.8.py
ga_api/hyper_log_log.py
ga_api_client_uf018127-0.2.4.dist-info/LICENSE
ga_api_client_uf018127-0.2.4.dist-info/METADATA
ga_api_client_uf018127-0.2.4.dist-info/WHEEL
ga_api_client_uf018127-0.2.4.dist-info/top_level.txt
ga_api_client_uf018127-0.2.4.dist-info/RECORD
