Metadata-Version: 2.1
Name: ga-api-client-uf018127
Version: 0.2.4
Summary: GenieAnalytics API client
Home-page: https://github.com/uf018127/ga-api-client
Author: Jacob Chiang
Author-email: jacob@genie-networks.com
Classifier: Programming Language :: Python :: 3
Classifier: License :: OSI Approved :: MIT License
Classifier: Operating System :: OS Independent
Requires-Python: >=3.9
License-File: LICENSE
